easy_csv_logging/__init__.py
easy_csv_logging/easy_csv_logging.py
easy_csv_logging-0.1.3.dist-info/METADATA
easy_csv_logging-0.1.3.dist-info/WHEEL
easy_csv_logging-0.1.3.dist-info/top_level.txt
easy_csv_logging-0.1.3.dist-info/RECORD
