Metadata-Version: 2.4
Name: easy-csv-logging
Version: 0.1.3
Summary: Simple CSV logging and viewing
Author: Anton Axelson
License-Expression: MIT
Requires-Python: >=3.8
Requires-Dist: pandas
Requires-Dist: rich
